{
  "bone": 0,
  "dog_food": 0,
  "dogs": [{"ID": "dog", "level": 1}],
  "items": [],
  "passed_level": -1,
  "passives": [],
  "selected_battlefield_id": "level1",
  "selected_level": 0,
  "selected_team": 0,
  "settings": { "music": {"volume": 60, "mute": false}, "sound_fx": {"volume": 50, "mute": false}, "language": "vi", "key_binding_overwrites": {} },
  "skills": [],
  "teams": [
	{
	  "dog_ids": ["dog", null, null, null, null, null, null, null, null, null],
	  "skill_ids": [null, null, null]
	}
  ]
}
